space/__init__.py
space/function.py
space/layer.py
space/model.py
space/train.py
space/utils.py
space_srt-0.7.0.dist-info/LICENSE
space_srt-0.7.0.dist-info/METADATA
space_srt-0.7.0.dist-info/WHEEL
space_srt-0.7.0.dist-info/top_level.txt
space_srt-0.7.0.dist-info/RECORD
