Metadata-Version: 2.1
Name: space-srt
Version: 0.7.0
Summary: SPatial transcriptomics Analysis via Cell Embedding
Author-email: Yuzhe Li <liyuzhezju@gmail.com>
Project-URL: Homepage, https://github.com/zhangqf-lab/SPACE
Project-URL: Bug Tracker, https://github.com/zhangqf-lab/SPACE/issues
Classifier: Programming Language :: Python :: 3
Classifier: License :: OSI Approved :: MIT License
Classifier: Operating System :: OS Independent
Classifier: Development Status :: 4 - Beta
Classifier: Intended Audience :: Science/Research
Classifier: Topic :: Scientific/Engineering :: Bio-Informatics
Requires-Python: >3.7.0
License-File: LICENSE
Requires-Dist: build
Requires-Dist: packaging
Requires-Dist: pyparsing
Requires-Dist: tomli
Requires-Dist: numpy
Requires-Dist: pandas
Requires-Dist: scipy
Requires-Dist: scikit-learn
Requires-Dist: scanpy
Requires-Dist: tqdm
Requires-Dist: matplotlib
Requires-Dist: leidenalg
Requires-Dist: squidpy
Requires-Dist: networkx
